texplotlib/__init__.py
texplotlib/module.py
texplotlib-0.5.7.dist-info/LICENSE
texplotlib-0.5.7.dist-info/METADATA
texplotlib-0.5.7.dist-info/WHEEL
texplotlib-0.5.7.dist-info/top_level.txt
texplotlib-0.5.7.dist-info/RECORD
