Metadata-Version: 2.1
Name: texplotlib
Version: 0.5.7
Summary: Package for .tex figures
Home-page: UNKNOWN
Author: Mostafa Ayaz
Author-email: m.ayaz@email.kntu.ac.ir
License: UNKNOWN
Platform: UNKNOWN
Requires-Python: >=3.6
License-File: LICENSE
Requires-Dist: matplotlib (>=3.1.0)
